{
  "pages": [
    {
      "title": "Home",
      "path": "/",
      "content": "Welcome to The Free Life - A wiki for information on living without or with less money."
    },
    {
      "title": "Free Money",
      "path": "/Main/free-money",
      "content": "Information about obtaining free money and financial assistance."
    },
    {
      "title": "Free Food/Meals",
      "path": "/Main/free-food",
      "content": "Information about obtaining free food and meals."
    },
    {
      "title": "Free Clothing",
      "path": "/Main/free-clothing",
      "content": "Information about obtaining free clothing."
    },
    {
      "title": "Free Services",
      "path": "/Main/free-services",
      "content": "Information about free services available."
    },
    {
      "title": "Free Financial Services",
      "path": "/Main/free-financial-services",
      "content": "Information about free financial services."
    },
    {
      "title": "Free Lodging",
      "path": "/Main/free-lodging",
      "content": "Information about free lodging and accommodation."
    },
    {
      "title": "Free Transport",
      "path": "/Main/free-transport",
      "content": "Information about free transportation options."
    },
    {
      "title": "Free Furniture",
      "path": "/Main/free-furniture",
      "content": "Information about obtaining free furniture."
    },
    {
      "title": "Free Car",
      "path": "/Main/free-car",
      "content": "Information about obtaining free or very low-cost vehicles."
    }
  ]
}
